custom_logger/__init__.py
custom_logger/custom_logger.py
custom_logger_cloudcity-1.0.4.dist-info/METADATA
custom_logger_cloudcity-1.0.4.dist-info/WHEEL
custom_logger_cloudcity-1.0.4.dist-info/top_level.txt
custom_logger_cloudcity-1.0.4.dist-info/RECORD
