Metadata-Version: 2.1
Name: custom-logger-cloudcity
Version: 1.0.4
Summary: UNKNOWN
Home-page: https://gitlab.com/dqna/custom-logger-cloudcity
License: UNKNOWN
Platform: UNKNOWN
Requires-Python: >=3.8
Requires-Dist: google-cloud-logging (==2.5.0)
